grokcore.message-4.1-py3.12-nspkg.pth
grokcore/message/README.rst
grokcore/message/__init__.py
grokcore/message/configure.zcml
grokcore/message/ftesting.zcml
grokcore/message/ram.zcml
grokcore/message/registrations.py
grokcore/message/sources.py
grokcore/message/tests.py
grokcore/message/utils.py
grokcore_message-4.1.dist-info/licenses/LICENSE.txt
grokcore_message-4.1.dist-info/METADATA
grokcore_message-4.1.dist-info/WHEEL
grokcore_message-4.1.dist-info/namespace_packages.txt
grokcore_message-4.1.dist-info/top_level.txt
grokcore_message-4.1.dist-info/RECORD
