Metadata-Version: 2.4
Name: grokcore.message
Version: 4.1
Summary: Grok messaging machinery
Home-page: https://github.com/zopefoundation/grokcore.message
Author: Grok Team
Author-email: grok-dev@zope.dev
License: ZPL-2.1
Keywords: Grok Messages
Classifier: Development Status :: 5 - Production/Stable
Classifier: Environment :: Web Environment
Classifier: Framework :: Zope :: 3
Classifier: Intended Audience :: Developers
Classifier: License :: OSI Approved :: Zope Public License
Classifier: Natural Language :: English
Classifier: Operating System :: OS Independent
Classifier: Programming Language :: Python
Classifier: Programming Language :: Python :: 3
Classifier: Programming Language :: Python :: 3.9
Classifier: Programming Language :: Python :: 3.10
Classifier: Programming Language :: Python :: 3.11
Classifier: Programming Language :: Python :: 3.12
Classifier: Programming Language :: Python :: 3.13
Classifier: Programming Language :: Python :: Implementation
Classifier: Programming Language :: Python :: Implementation :: CPython
Classifier: Programming Language :: Python :: Implementation :: PyPy
Classifier: Topic :: Internet :: WWW/HTTP
Requires-Python: >=3.9
License-File: LICENSE.txt
Requires-Dist: setuptools
Requires-Dist: grokcore.component>=2.5
Requires-Dist: z3c.flashmessage
Requires-Dist: zope.component
Provides-Extra: test
Requires-Dist: zope.publisher; extra == "test"
Requires-Dist: zope.security; extra == "test"
Requires-Dist: zope.session>=5.1; extra == "test"
Requires-Dist: zope.testrunner; extra == "test"
Dynamic: author
Dynamic: author-email
Dynamic: classifier
Dynamic: description
Dynamic: home-page
Dynamic: keywords
Dynamic: license
Dynamic: license-file
Dynamic: provides-extra
Dynamic: requires-dist
Dynamic: requires-python
Dynamic: summary
